speak_now/__init__.py
speak_now/app.py
speak_now/cli.py
speak_now/config.py
speak_now/gui_notification.py
speak_now/hotkey_manager.py
speak_now/text_cache.py
speak_now/utils.py
speak_now-0.1.3.dist-info/METADATA
speak_now-0.1.3.dist-info/WHEEL
speak_now-0.1.3.dist-info/entry_points.txt
speak_now-0.1.3.dist-info/licenses/LICENSE
speak_now-0.1.3.dist-info/RECORD
