Metadata-Version: 2.4
Name: speak-now
Version: 0.1.3
Summary: A locally-hosted, low-latency speech-to-text solution with LLM integration.
Author-email: yada <trojblue@gmail.com>
License-File: LICENSE
Requires-Python: >=3.10
Requires-Dist: keyboard>=0.13.5
Requires-Dist: numpy>=1.26.4
Requires-Dist: pyaudio>=0.2.14
Requires-Dist: pyautogui>=0.9.54
Requires-Dist: pyperclip>=1.9.0
Requires-Dist: realtimestt>=0.3.95
Requires-Dist: requests>=2.32.3
Requires-Dist: toml>=0.10.2
